martian/README.rst
martian/__init__.py
martian/components.py
martian/context.py
martian/context.rst
martian/core.py
martian/core.rst
martian/directive.py
martian/directive.rst
martian/edgecase.rst
martian/error.py
martian/interfaces.py
martian/martiandirective.py
martian/scan.py
martian/scan.rst
martian/testing.py
martian/util.py
martian/tests/__init__.py
martian/tests/public_methods_from_class.rst
martian/tests/scan_for_classes.rst
martian/tests/test_all.py
martian/tests/scanforclasses/__init__.py
martian/tests/scanforclasses/test1.py
martian/tests/scanforclasses/test2.py
martian/tests/scanforclasses/test3.py
martian/tests/scanforclasses/test4.py
martian/tests/stoneage/__init__.py
martian/tests/stoneage/cave.py
martian/tests/stoneage/hunt/__init__.py
martian/tests/stoneage/hunt/mammoth.py
martian/tests/stoneage/hunt/mammoth_templates/index.pt
martian/tests/stoneage/notpackage/dummy.py
martian/tests/stoneage/painting/__init__.py
martian/tests/testpackage/__init__.py
martian/tests/testpackage/animal.py
martian/tests/testpackage/one.py
martian/tests/testpackage/two.py
martian/tests/testpackage/alpha/__init__.py
martian/tests/testpackage/beta/__init__.py
martian/tests/testpackage/beta/three.py
martian/tests/with__main__/__init__.py
martian/tests/with__main__/__main__.py
martian/tests/with__main__/package.py
martian/tests/withbogusmodules/.bogus.py
martian/tests/withbogusmodules/1alsobogus.py
martian/tests/withbogusmodules/__init__.py
martian/tests/withbogusmodules/nonbogus.py
martian/tests/withbogusmodules/.bogussubpackage/__init__.py
martian/tests/withbogusmodules/subpackage/__init__.py
martian/tests/withpyconly/__init__.py
martian/tests/withpyconly/foo.py
martian/tests/withpyconly/subpackage/__init__.py
martian/tests/withtestsmodules/__init__.py
martian/tests/withtestsmodules/ftests.py
martian/tests/withtestsmodules/tests.py
martian/tests/withtestsmodules/subpackage/__init__.py
martian/tests/withtestspackages/__init__.py
martian-2.0.post1.dist-info/LICENSE.txt
martian-2.0.post1.dist-info/METADATA
martian-2.0.post1.dist-info/WHEEL
martian-2.0.post1.dist-info/top_level.txt
martian-2.0.post1.dist-info/RECORD
