Metadata-Version: 2.1
Name: martian
Version: 2.0.post1
Summary: Embedding of configuration information in Python code.
Home-page: https://github.com/zopefoundation/martian
Author: Grok project
Author-email: grok-dev@zope.org
License: ZPL
Classifier: Development Status :: 6 - Mature
Classifier: Intended Audience :: Developers
Classifier: License :: OSI Approved :: Zope Public License
Classifier: Operating System :: OS Independent
Classifier: Programming Language :: Python :: 3
Classifier: Programming Language :: Python :: 3.7
Classifier: Programming Language :: Python :: 3.8
Classifier: Programming Language :: Python :: 3.9
Classifier: Programming Language :: Python :: 3.10
Classifier: Programming Language :: Python :: 3.11
Classifier: Programming Language :: Python :: Implementation :: CPython
Classifier: Programming Language :: Python :: Implementation :: PyPy
Classifier: Topic :: Utilities
Requires-Python: >=3.7
Provides-Extra: test
License-File: LICENSE.txt
